<?xml version="1.0" encoding="UTF-8"?>
<vra xmlns="http://www.vraweb.org/vracore4.htm" xmlns:xsi="http://www.w3.org/2001/XMLSchema-instance" xsi:schemaLocation="http://www.vraweb.org/vracore4.htm http://cluster-schemas.uni-hd.de/vra-strictCluster.xsd">
    <work id="w_111f9755-334a-4ed2-856d-566049d57f07" source="Kurs" refid="c_538d2770-b2f5-4167-99ad-b081d9686709">
        <agentSet>
            <agent pref="true" dataDate="2016-02-16-14-05-21">
                <name refid="100642444" type="personal" vocab="viaf">unknown South Netherlandish</name>
                <role type="code" vocab="marcrelator">dsr</role>
            </agent>
        </agentSet>
        <culturalContextSet>
            <culturalContext extent="AAT 300111184" pref="false">Flemish (culture or style)</culturalContext>
        </culturalContextSet>
        <dateSet>
            <date pref="true" type="creation" dataDate="2016-02-16-14-12-09">
                <earliestDate>
                    <date>1495</date>
                </earliestDate>
                <latestDate>
                    <date>1505</date>
                </latestDate>
            </date>
        </dateSet>
        <descriptionSet>
            <description pref="false" dataDate="2016-02-16-14-37-09">
                <text>From the Unicorn Hunt series; the story merges pagan and Christian iconography; Unicorn was captured after resting his head in a virgin’s lap, as Christ sacrificed his divinity to become human through a virgin; this scene represents the Resurrected Christ; other symbolism, including the fecund flora, suggests this tapestry celebrated a marriage. The unicorn also represents the beloved tamed. He is tethered to a tree and constrained by a fence, but the chain is not secure and the fence is low enough to leap over: The unicorn could escape if he wished. Clearly, however, his confinement is a happy one, to which the ripe, seed-laden pomegranates in the tree—a medieval symbol of fertility and marriage—testify.</text>
                <author>
                    <name refid="131347215" type="corporate" vocab="viaf">Visual Resources Association</name>
                    <role type="code" vocab="marcrelator">aut</role>
                </author>
            </description>
            <description extent="museum label" href="http://www.metmuseum.org/collection/the-collection-online/search/467642" pref="false" source="Metropolitan Museum of Art" dataDate="2016-02-16-14-37-42">
                <text>The seven individual hangings known as "The Unicorn Tapestries," are among the most beautiful and complex works of art from the late Middle Ages that survive. Luxuriously woven in fine wool and silk with silver and gilded threads, the tapestries vividly depict scenes associated with a hunt for the elusive, magical unicorn. 

"The Unicorn in Captivity" may have been created as a single image rather than part of a series. In this instance, the unicorn probably represents the beloved tamed. He is tethered to a tree and constrained by a fence, but the chain is not secure and the fence is low enough to leap over: The unicorn could escape if he wished. Clearly, however, his confinement is a happy one, to which the ripe, seed-laden pomegranates in the tree—a medieval symbol of fertility and marriage—testify. The red stains on his flank do not appear to be blood, as there are no visible wounds like those in the hunting series; rather, they represent juice dripping from bursting pomegranates above. Many of the other plants represented here, such as wild orchid, bistort, and thistle, echo this theme of marriage and procreation: they were acclaimed in the Middle Ages as fertility aids for both men and women. Even the little frog, nestled among the violets at the lower right, was cited by medieval writers for its noisy mating.</text>
                <author>
                    <name refid="126238294" type="corporate" vocab="viaf">Metropolitan museum of art (New York, N.Y.)</name>
                    <role type="code" vocab="marcrelator">aut</role>
                </author>
            </description>
        </descriptionSet>
        <inscriptionSet>
            <inscription href="http://www.metmuseum.org/collection/the-collection-online/search/467642" pref="false" source="Metropolitan Museum of Art - Collection Online" dataDate="2016-02-16-15-47-27">
                <author refid="100642444" vocab="viaf">unknown South Netherlandish</author>
                <position>center and three corners</position>
                <text type="other">AE</text>
            </inscription>
        </inscriptionSet>
        <locationSet>
            <location pref="false" type="repository" dataDate="2016-02-16-14-40-21">
                <refid type="accession">37.80.6</refid>
                <name refid="126238294" type="corporate" vocab="viaf">Metropolitan museum of art (New York, N.Y.)</name>
            </location>
            <location pref="false" type="creation" dataDate="2016-02-16-14-41-31">
                <name refid="7007868" type="geographic" vocab="tgn">Bruxelles</name>
            </location>
        </locationSet>
        <materialSet>
            <material pref="false" refid="300014072" type="medium" vocab="aat">silk</material>
            <material pref="false" refid="300014074" type="medium" vocab="aat">wool</material>
        </materialSet>
        <measurementsSet>
            <measurements pref="false" type="height" unit="cm">368</measurements>
            <measurements pref="false" type="width" unit="cm">251.5</measurements>
            <measurements pref="false" type="height" unit="in">144 7/8</measurements>
            <measurements pref="false" type="width" unit="in">99</measurements>
        </measurementsSet>
        <relationSet>
            <relation pref="false" relids="w_998dcc90-a0ae-4f73-9f41-910bf5c4fb83" type="partnerInSetWith">The Hunters Enter the Woods</relation>
            <relation pref="false" relids="w_76afc7a1-d257-462e-981f-7729bd4c33fb" type="partnerInSetWith">The Unicorn is Killed and Brought to the Castle</relation>
            <relation pref="false" relids="w_4b23f0f9-dc19-4c55-bf54-ab4a4cac2e93" type="partnerInSetWith">The Unicorn Defends Itself</relation>
            <relation pref="false" relids="w_c035c048-a040-4296-9972-e3425515ac2b" type="partnerInSetWith">The Unicorn is Attacked</relation>
            <relation pref="false" relids="w_c925ba01-3723-42d3-8755-da337b0bfbc3" type="partnerInSetWith">The Unicorn is Found</relation>
            <relation pref="true" relids="i_8843ee07-dc38-4fd2-a8fb-5ba576c837c0" source="Tamboti" type="imageIs">general view</relation>
        </relationSet>
        <sourceSet>
            <source pref="true">
                <refid type="URI">http://cco.vrafoundation.org/index.php/toolkit/index_of_examples/category_examples_2_decorative_arts_and_utilitarian_objects/example_123_tapestry_part_of_series</refid>
                <name type="electronic">Cataloging Cultural Objects Commons</name>
            </source>
            <source pref="false" dataDate="2016-02-16-16-54-19">
                <refid type="URI">http://www.metmuseum.org/collection/the-collection-online/search/467642</refid>
                <name type="electronic">Metropolitan Museum of Art - The Collection Online</name>
            </source>
        </sourceSet>
        <subjectSet>
            <subject pref="false" refid="300054168" vocab="aat" dataDate="2016-02-16-16-57-34">
                <term type="descriptiveTopic">decorative arts</term>
            </subject>
            <subject pref="false" refid="300379149" vocab="aat" dataDate="2016-02-16-15-08-49">
                <term type="iconographicTopic">fertility</term>
            </subject>
            <subject pref="false" refid="300055475" vocab="aat">
                <term type="iconographicTopic">marriage (social construct)</term>
            </subject>
            <subject pref="false" refid="300055866" vocab="aat" dataDate="2016-02-16-14-58-37">
                <term type="conceptTopic">allegory (artistic device)</term>
            </subject>
            <subject pref="false" refid="300379595" vocab="aat" dataDate="2016-07-06">
                <term type="iconographicTopic">unicorns</term>
            </subject>
            <subject pref="false" refid="300189557" vocab="aat">
                <term type="iconographicTopic">female</term>
            </subject>
            <subject pref="false" refid="300256501" vocab="aat" dataDate="2016-07-06">
                <term type="iconographicTopic">Passion cycles</term>
            </subject>
            <subject pref="false" refid="uuid-9e0abfbc-5cff-5fe2-8420-3830087bc722" vocab="local">
                <term type="iconographicTopic">virginity</term>
            </subject>
        </subjectSet>
        <techniqueSet>
            <technique pref="false" refid="300053642" vocab="aat">weaving</technique>
        </techniqueSet>
        <titleSet>
            <title href="http://www.metmuseum.org/collection/the-collection-online/search/467642" pref="true" source="Metropolitan Museum of Art" type="repository">The Unicorn in Captivity (from the Unicorn Tapestries)</title>
            <title pref="false" type="other">Unicorn in Captivity</title>
        </titleSet>
        <worktypeSet>
            <worktype pref="false" refid="300205002" vocab="aat">tapestries</worktype>
            <worktype pref="false" refid="300014063" vocab="aat">textiles</worktype>
        </worktypeSet>
    </work>
</vra>